setup.py
bobos3/__init__.py
bobos3/bobos3.py
bobos3.egg-info/PKG-INFO
bobos3.egg-info/SOURCES.txt
bobos3.egg-info/dependency_links.txt
bobos3.egg-info/not-zip-safe
bobos3.egg-info/requires.txt
bobos3.egg-info/top_level.txt