Metadata-Version: 1.1
Name: bobos3
Version: 0.1.0
Summary: bobos3 is a simple library for accessing and manipulating objects via S3 API
Home-page: http://github.com/contman/bobos3
Author: CONTMAN sp. z o.o.
Author-email: opensource@contman.pl
License: MIT
Platform: UNKNOWN
Classifier: Development Status :: 4 - Beta
Classifier: Intended Audience :: Developers
Classifier: Topic :: Software Development :: Libraries :: Python Modules
Classifier: License :: OSI Approved :: MIT License
Classifier: Programming Language :: Python :: 2
Classifier: Programming Language :: Python :: 2.7
